crnde/__init__.py
crnde/crnde.py
crnde-1.0.dist-info/licenses/license
crnde-1.0.dist-info/METADATA
crnde-1.0.dist-info/WHEEL
crnde-1.0.dist-info/top_level.txt
crnde-1.0.dist-info/RECORD
