Metadata-Version: 2.4
Name: crnde
Version: 1.0
Summary: fast encryptic and decrpytic
Author-email: howShouldIChosseMyUsername <trademark2179@gmail.com>
License: MIT
Requires-Python: >=3.7
License-File: license
Dynamic: license-file
